edgar/__init__.py
edgar/dataloader.py
edgar/document.py
edgar/downloader.py
edgar/html.py
edgar/metadata_manager.py
edgar/parser.py
edgar/pipeline.py
edgar/subheader_parser_8k.py
edgar/wrappers.py
edgar_doc_parser-0.2.2.post1.dist-info/LICENSE
edgar_doc_parser-0.2.2.post1.dist-info/METADATA
edgar_doc_parser-0.2.2.post1.dist-info/WHEEL
edgar_doc_parser-0.2.2.post1.dist-info/top_level.txt
edgar_doc_parser-0.2.2.post1.dist-info/RECORD
