Metadata-Version: 2.1
Name: edgar-doc-parser
Version: 0.2.2.post1
Summary: Download, extraction, and parsing of documents available through the Securities and Trade Commission's EDGAR database
Author: Yiting Li, Nachuan Zhao, Kelsey Yew
Author-email: Kamil Krukowski <Kamil.Krukowski@tufts.edu>
Maintainer-email: Kamil Krukowski <Kamil.Krukowski@tufts.edu>
Project-URL: Homepage, https://github.com/kamilkrukowski/EDGAR-DOC-PARSER
Project-URL: Bug Tracker, https://github.com/kamilkrukowski/EDGAR-DOC-PARSER/issues
Classifier: Programming Language :: Python :: 3
Classifier: License :: OSI Approved :: MIT License
Classifier: Operating System :: OS Independent
Requires-Python: >=3.7
License-File: LICENSE
Requires-Dist: secedgar (==0.4.0)
Requires-Dist: pyyaml (==6.0)
Requires-Dist: numpy (==1.24.1)
Requires-Dist: pandas (==1.5.3)
